setup.py
apache_log_parser/__init__.py
apache_log_parser/tests.py
apache_log_parser.egg-info/PKG-INFO
apache_log_parser.egg-info/SOURCES.txt
apache_log_parser.egg-info/dependency_links.txt
apache_log_parser.egg-info/requires.txt
apache_log_parser.egg-info/top_level.txt